<?xml version="1.0" encoding="UTF-8"?>
<?xml-stylesheet type="text/xsl" href="http://www.revistas.usp.br/lib/pkp/xml/oai2.xsl" ?>
<OAI-PMH xmlns="http://www.openarchives.org/OAI/2.0/"
	xmlns:xsi="http://www.w3.org/2001/XMLSchema-instance"
	xsi:schemaLocation="http://www.openarchives.org/OAI/2.0/
		http://www.openarchives.org/OAI/2.0/OAI-PMH.xsd">
	<responseDate>2015-05-17T21:33:14Z</responseDate>
	<request verb="GetRecord" metadataPrefix="oai_dc" identifier="oai:www.revistas.usp.br:article/42376">http://www.revistas.usp.br/incid/oai</request>
	<GetRecord>
		<record>
			<header>
				<identifier>oai:www.revistas.usp.br:article/42376</identifier>
				<datestamp>2015-04-14T11:19:16Z</datestamp>
				<setSpec>incid:REL</setSpec>
			</header>
			<metadata>
<oai_dc:dc
	xmlns:oai_dc="http://www.openarchives.org/OAI/2.0/oai_dc/"
	xmlns:dc="http://purl.org/dc/elements/1.1/"
	xmlns:xsi="http://www.w3.org/2001/XMLSchema-instance"
	xsi:schemaLocation="http://www.openarchives.org/OAI/2.0/oai_dc/
	http://www.openarchives.org/OAI/2.0/oai_dc.xsd">
	<dc:title xml:lang="pt-BR">Observatório de estudos em Ciência da Informação: mapas, redes, rizomas e labirintos</dc:title>
	<dc:title xml:lang="en-US">Centre for Studies in Science Information: maps, networks, rhizomes and mazes</dc:title>
	<dc:creator>de Souza Gracioso, Luciana; UFSCar</dc:creator>
	<dc:subject xml:lang="pt-BR">Ciência da Informação</dc:subject>
	<dc:description xml:lang="pt-BR"> Observat&amp;oacute;rio de estudos em Ci&amp;ecirc;ncia da Informa&amp;ccedil;&amp;atilde;o: mapas, redes, rizomas e labirintos</dc:description>
	<dc:description xml:lang="en-US">Centre for Studies in Science Information: maps, networks, rhizomes and mazes</dc:description>
	<dc:publisher xml:lang="pt-BR">Universidade de São Paulo. Faculdade de Filosofia, Ciências e Letras de Ribeirão Preto</dc:publisher>
	<dc:date>2012-06-28</dc:date>
	<dc:type>info:eu-repo/semantics/article</dc:type>
	<dc:type>info:eu-repo/semantics/publishedVersion</dc:type>
	<dc:type xml:lang="pt-BR"></dc:type>
	<dc:type xml:lang="en-US"></dc:type>
	<dc:format>application/pdf</dc:format>
	<dc:identifier>http://www.revistas.usp.br/incid/article/view/42376</dc:identifier>
	<dc:identifier>10.11606/issn.2178-2075.v3i1p168-171</dc:identifier>
	<dc:source xml:lang="pt-BR">InCID: Revista de Ciência da Informação e Documentação; v. 3, n. 1 (2012); 168-171</dc:source>
	<dc:source>2178-2075</dc:source>
	<dc:language>por</dc:language>
	<dc:relation>http://www.revistas.usp.br/incid/article/view/42376/46047</dc:relation>
</oai_dc:dc>
			</metadata>
		</record>
	</GetRecord>
</OAI-PMH>
